BUILD.rst
COPYRIGHT.txt
INSTALL.rst
LICENSE.txt
MANIFEST.in
README
README.rst
SELENIUM_COPYRIGHT.txt
selenium.bmp
setup.cfg
setup.py
demo/log.html
demo/package.py
demo/report.html
demo/rundemo.py
demo/demoapp/server.py
demo/demoapp/html/demo.css
demo/demoapp/html/error.html
demo/demoapp/html/index.html
demo/demoapp/html/welcome.html
demo/login_tests/invalid_login.txt
demo/login_tests/resource.txt
demo/login_tests/valid_login.txt
doc/Selenium2Library.html
src/ez_setup.py
src/Selenium2Library/__init__.py
src/Selenium2Library/version.py
src/Selenium2Library/webdrivermonkeypatches.py
src/Selenium2Library/keywords/__init__.py
src/Selenium2Library/keywords/_browsermanagement.py
src/Selenium2Library/keywords/_cookie.py
src/Selenium2Library/keywords/_element.py
src/Selenium2Library/keywords/_formelement.py
src/Selenium2Library/keywords/_javascript.py
src/Selenium2Library/keywords/_logging.py
src/Selenium2Library/keywords/_runonfailure.py
src/Selenium2Library/keywords/_screenshot.py
src/Selenium2Library/keywords/_selectelement.py
src/Selenium2Library/keywords/_tableelement.py
src/Selenium2Library/keywords/_waiting.py
src/Selenium2Library/keywords/keywordgroup.py
src/Selenium2Library/locators/__init__.py
src/Selenium2Library/locators/elementfinder.py
src/Selenium2Library/locators/tableelementfinder.py
src/Selenium2Library/locators/windowmanager.py
src/Selenium2Library/resources/firefoxprofile/localstore.rdf
src/Selenium2Library/resources/firefoxprofile/prefs.js
src/Selenium2Library/utils/__init__.py
src/Selenium2Library/utils/browsercache.py
src/robotframework_selenium2library.egg-info/PKG-INFO
src/robotframework_selenium2library.egg-info/SOURCES.txt
src/robotframework_selenium2library.egg-info/dependency_links.txt
src/robotframework_selenium2library.egg-info/requires.txt
src/robotframework_selenium2library.egg-info/top_level.txt